scenario_generator/__init__.py
scenario_generator/curated.py
scenario_generator/gbm_forecast.py
scenario_generator/mcmc_forecast.py
scenario_generator/utils.py
scenario_generator-0.1.0.dist-info/LICENSE
scenario_generator-0.1.0.dist-info/METADATA
scenario_generator-0.1.0.dist-info/WHEEL
scenario_generator-0.1.0.dist-info/top_level.txt
scenario_generator-0.1.0.dist-info/RECORD
