Metadata-Version: 2.1
Name: scenario-generator
Version: 0.1.0
Summary: Scenario generator for understanding Filecoin dynamics
Home-page: https://github.com/protocol/scenario-generator
Author: Kiran Karra, Tom Mellan
Author-email: kiran.karra@protocol.ai, tom.mellan@protocol.ai
License: MIT License
Requires-Python: >=3
License-File: LICENSE
Requires-Dist: numpy
Requires-Dist: pandas
Requires-Dist: numpyro
Requires-Dist: jax
Requires-Dist: mechaFIL
